signalrcore1/__init__.py
signalrcore1/helpers.py
signalrcore1/hub_connection_builder.py
signalrcore1/subject.py
signalrcore1/hub/__init__.py
signalrcore1/hub/auth_hub_connection.py
signalrcore1/hub/base_hub_connection.py
signalrcore1/hub/errors.py
signalrcore1/hub/handlers.py
signalrcore1/messages/__init__.py
signalrcore1/messages/base_message.py
signalrcore1/messages/cancel_invocation_message.py
signalrcore1/messages/close_message.py
signalrcore1/messages/completion_message.py
signalrcore1/messages/invocation_message.py
signalrcore1/messages/message_type.py
signalrcore1/messages/ping_message.py
signalrcore1/messages/stream_invocation_message.py
signalrcore1/messages/stream_item_message.py
signalrcore1/messages/handshake/__init__.py
signalrcore1/messages/handshake/request.py
signalrcore1/messages/handshake/response.py
signalrcore1/protocol/__init__.py
signalrcore1/protocol/base_hub_protocol.py
signalrcore1/protocol/json_hub_protocol.py
signalrcore1/protocol/messagepack_protocol.py
signalrcore1/protocol/handshake/__init__.py
signalrcore1/transport/__init__.py
signalrcore1/transport/base_transport.py
signalrcore1/transport/websockets/__init__.py
signalrcore1/transport/websockets/connection.py
signalrcore1/transport/websockets/reconnection.py
signalrcore1/transport/websockets/websocket_transport.py
signalrcore1-1.1.7.dist-info/licenses/LICENSE
test/__init__.py
test/base_test_case.py
test/client_streaming_test.py
test/configuration_test.py
test/open_close_test.py
test/reconnection_test.py
test/send_auth_errors_test.py
test/send_auth_test.py
test/send_test.py
test/streaming_test.py
signalrcore1-1.1.7.dist-info/METADATA
signalrcore1-1.1.7.dist-info/WHEEL
signalrcore1-1.1.7.dist-info/top_level.txt
signalrcore1-1.1.7.dist-info/RECORD
