Metadata-Version: 2.4
Name: signalrcore1
Version: 1.1.7
Summary: A Python SignalR Core client(json and messagepack), with invocation auth and two way streaming. Compatible with azure / serverless functions. Also with automatic reconnect and manually reconnect.
Home-page: https://github.com/mandrewcito/signalrcore
Author: sipanohanyan
Author-email: sipanohanyan@gmail.com
Keywords: signalr core client 3.1
Classifier: Programming Language :: Python :: 3.14
License-File: LICENSE
Requires-Dist: requests>=2.32.5
Requires-Dist: websocket-client>=1.9.0
Requires-Dist: msgpack==1.1.2
Dynamic: author
Dynamic: author-email
Dynamic: classifier
Dynamic: description
Dynamic: description-content-type
Dynamic: home-page
Dynamic: keywords
Dynamic: license-file
Dynamic: requires-dist
Dynamic: summary
